mcfc/__about__.py
mcfc/__init__.py
mcfc/main.py
mcfc-3.0.5.dist-info/METADATA
mcfc-3.0.5.dist-info/WHEEL
mcfc-3.0.5.dist-info/licenses/LICENSE.txt
mcfc-3.0.5.dist-info/RECORD
