Metadata-Version: 2.1
Name: mcfc
Version: 3.0.5
Summary: Text formatting using Minecraft color codes.
Project-URL: Documentation, https://github.com/woidzero/mcfc#readme
Project-URL: Issues, https://github.com/woidzero/mcfc/issues
Project-URL: Source, https://github.com/woidzero/mcfc
Author-email: woidzero <woidzerov@gmail.com>
License-Expression: MIT
License-File: LICENSE.txt
Keywords: cmd,color,command prompt,console,terminal
Classifier: Development Status :: 5 - Production/Stable
Classifier: Environment :: Console
Classifier: Programming Language :: Python
Classifier: Programming Language :: Python :: 3.7
Classifier: Programming Language :: Python :: 3.8
Classifier: Programming Language :: Python :: 3.9
Classifier: Programming Language :: Python :: 3.10
Classifier: Programming Language :: Python :: 3.11
Classifier: Programming Language :: Python :: Implementation :: CPython
Classifier: Programming Language :: Python :: Implementation :: PyPy
Requires-Python: >=3.7
